setup.cfg
setup.py
luko_rada_package_2/__init__.py
luko_rada_package_2/descriptors.py
luko_rada_package_2/rada_consoles.py
luko_rada_package_2/rada_databases.py
luko_rada_package_2/rada_factories.py
luko_rada_package_2/rada_metaclass.py
luko_rada_package_2/rada_models.py
luko_rada_package_2/utils.py
luko_rada_package_2/verh_rada.py
luko_rada_package_2.egg-info/PKG-INFO
luko_rada_package_2.egg-info/SOURCES.txt
luko_rada_package_2.egg-info/dependency_links.txt
luko_rada_package_2.egg-info/entry_points.txt
luko_rada_package_2.egg-info/not-zip-safe
luko_rada_package_2.egg-info/top_level.txt