Metadata-Version: 1.0
Name: luko-rada-package-2
Version: 0.6.dev0
Summary: Rada with abstract factory
Home-page: UNKNOWN
Author: Luko Kopach
Author-email: UNKNOWN
License: UNKNOWN
Keywords: abstract factory python itea
Platform: UNKNOWN
